awd/__init__.py
awdtools-0.0.1b0.dist-info/METADATA
awdtools-0.0.1b0.dist-info/WHEEL
awdtools-0.0.1b0.dist-info/top_level.txt
awdtools-0.0.1b0.dist-info/RECORD
