Metadata-Version: 2.1
Name: awdtools
Version: 0.0.1b0
Summary: Tools for easy CTF AWD
Home-page: https://github.com/summershrimp/awdtools
Author: Yibai Zhang
Author-email: xm1994@gmail.com
License: UNKNOWN
Platform: UNKNOWN
Classifier: Programming Language :: Python :: 2
Classifier: License :: OSI Approved :: GNU General Public License v2 (GPLv2)
Classifier: Operating System :: OS Independent
